LexData/__init__.py
LexData/claim.py
LexData/entity.py
LexData/form.py
LexData/language.py
LexData/languages.py
LexData/lexeme.py
LexData/sense.py
LexData/utils.py
LexData/version.py
LexData/wikidatasession.py
LexData-0.2.0.dist-info/LICENSE
LexData-0.2.0.dist-info/METADATA
LexData-0.2.0.dist-info/WHEEL
LexData-0.2.0.dist-info/top_level.txt
LexData-0.2.0.dist-info/RECORD
