Metadata-Version: 2.1
Name: LexData
Version: 0.2.0
Summary: A tiny package for editing Lexemes on Wikidata
Home-page: https://github.com/Nudin/LexData
Author: Michael F. Schoenitzer
Author-email: michael@schoenitzer.de
License: UNKNOWN
Platform: UNKNOWN
Classifier: Programming Language :: Python :: 3
Classifier: License :: OSI Approved :: MIT License
Classifier: Operating System :: OS Independent
Requires-Dist: requests
